sgd_sai/__init__.py
sgd_sai/__version__.py
sgd_sai/sgd_sai.py
sgd_sai-1.0.3.dist-info/LICENSE
sgd_sai-1.0.3.dist-info/METADATA
sgd_sai-1.0.3.dist-info/WHEEL
sgd_sai-1.0.3.dist-info/top_level.txt
sgd_sai-1.0.3.dist-info/RECORD
