Metadata-Version: 2.1
Name: sgd_sai
Version: 1.0.3
Summary: SGD-SaI Optimizer Implementation, designed for pytorch specificly.
Home-page: https://github.com/AnonymousAlethiometer/SGD_SaI
Author: Anonymous
Author-email: anonymous@anonymous.com
License: Apache Software License
Classifier: License :: OSI Approved :: Apache Software License
Classifier: Programming Language :: Python
Classifier: Programming Language :: Python :: 3
Classifier: Programming Language :: Python :: 3.6
Classifier: Programming Language :: Python :: Implementation :: CPython
Classifier: Programming Language :: Python :: Implementation :: PyPy
Requires-Python: >=3.6.0
License-File: LICENSE
